lyricfetcher/__init__.py
lyricfetcher/main.py
lyricfetcher/sources/AZlyrics.py
lyricfetcher/sources/__init__.py
lyricfetcher/sources/genius.py
lyricfetcher/sources/lyricswikia.py
lyricfetcher/sources/metrolyrics.py
lyricfetcher-0.5.dist-info/DESCRIPTION.rst
lyricfetcher-0.5.dist-info/METADATA
lyricfetcher-0.5.dist-info/RECORD
lyricfetcher-0.5.dist-info/WHEEL
lyricfetcher-0.5.dist-info/entry_points.txt
lyricfetcher-0.5.dist-info/metadata.json
lyricfetcher-0.5.dist-info/top_level.txt
