Metadata-Version: 2.0
Name: lyricfetcher
Version: 0.5
Summary: lyricfetcher
Home-page: http://github.com/bharatkalluri/lyricfetcher
Author: Bharat Kalluri
Author-email: bharatkalluri@protonmail.com
License: MIT
Platform: UNKNOWN
Requires-Dist: beautifulsoup4
Requires-Dist: bs4
Requires-Dist: lxml
Requires-Dist: requests
Requires-Dist: requests
